pika_wrapper/__init__.py
pika_wrapper/client.py
pika_wrapper-0.0.5.dist-info/LICENSE
pika_wrapper-0.0.5.dist-info/METADATA
pika_wrapper-0.0.5.dist-info/WHEEL
pika_wrapper-0.0.5.dist-info/top_level.txt
pika_wrapper-0.0.5.dist-info/RECORD
