Metadata-Version: 2.1
Name: pika-wrapper
Version: 0.0.5
Summary: Simple wrapper around Pika to make it easier to work with.
Home-page: https://github.com/2100992/pika_wrapper
Author: MrShved
Author-email: 2100992@gmail.com
License: UNKNOWN
Keywords: pika,rabbitmq,amqpy
Platform: UNKNOWN
Classifier: Programming Language :: Python
Classifier: License :: OSI Approved :: MIT License
Classifier: Development Status :: 3 - Alpha
Classifier: Intended Audience :: Developers
Requires-Python: >=3.6
License-File: LICENSE
